lawsql_tree_unit/__init__.py
lawsql_tree_unit/__main__.py
lawsql_tree_unit/body.py
lawsql_tree_unit/extract_details.py
lawsql_tree_unit/find_short_title.py
lawsql_tree_unit/unformatted.py
lawsql_tree_unit/utils.py
lawsql_tree_unit-0.0.3.dist-info/WHEEL
lawsql_tree_unit-0.0.3.dist-info/METADATA
lawsql_tree_unit-0.0.3.dist-info/RECORD
