Metadata-Version: 2.1
Name: lawsql-tree-unit
Version: 0.0.3
Summary: Format units for use in tree structures, e.g. Statutes, Codifications, etc.
Author: Marcelino G. Veloso III
Author-email: mars@veloso.one
Requires-Python: >=3.9,<4.0
Classifier: Programming Language :: Python :: 3
Classifier: Programming Language :: Python :: 3.9
Classifier: Programming Language :: Python :: 3.10
Requires-Dist: markdown2 (>=2.4.3,<3.0.0)
Requires-Dist: treeish (>=0.0.1,<0.0.2)
